prophetess_null/__init__.py
prophetess_null/extractor.py
prophetess_null/loader.py
prophetess_null/transformer.py
prophetess_null-1.0.2.dist-info/LICENSE
prophetess_null-1.0.2.dist-info/METADATA
prophetess_null-1.0.2.dist-info/WHEEL
prophetess_null-1.0.2.dist-info/entry_points.txt
prophetess_null-1.0.2.dist-info/top_level.txt
prophetess_null-1.0.2.dist-info/RECORD
