Metadata-Version: 2.1
Name: prophetess-null
Version: 1.0.2
Summary: Debug plugin for Prophetess
Home-page: https://github.com/vapor-ware/prophetess-null
Author: Marco Ceppi
Author-email: marco@vapor.io
License: GNU General Public License v3.0
Platform: UNKNOWN
Classifier: Environment :: Plugins
Classifier: Programming Language :: Python :: 3
Classifier: License :: OSI Approved :: GNU General Public License v3 (GPLv3)
Classifier: Operating System :: OS Independent
Requires-Python: >=3.6
